readlif/__init__.py
readlif/reader.py
readlif/utilities.py
readlif-0.6.6.dist-info/LICENSE
readlif-0.6.6.dist-info/METADATA
readlif-0.6.6.dist-info/WHEEL
readlif-0.6.6.dist-info/RECORD
