Metadata-Version: 2.1
Name: readlif
Version: 0.6.6
Summary: Fast Leica Image Format (LIF) file reader
License: GPLv3
Author: Nick Negretti
Requires-Python: >=3.9,<4.0
Classifier: License :: Other/Proprietary License
Classifier: Programming Language :: Python :: 3
Classifier: Programming Language :: Python :: 3.9
Classifier: Programming Language :: Python :: 3.10
Classifier: Programming Language :: Python :: 3.11
Classifier: Programming Language :: Python :: 3.12
Requires-Dist: beautifulsoup4 (>=4.12.3)
Requires-Dist: numpy (>=2.0.0)
Requires-Dist: pillow (>=7.2.0)
Project-URL: Homepage, https://github.com/arcadia-science/readlif
